prarabdha/__init__.py
prarabdha/api/__init__.py
prarabdha/api/app.py
prarabdha/api/dashboard.py
prarabdha/audio/__init__.py
prarabdha/audio/audio_cache.py
prarabdha/chats/__init__.py
prarabdha/chats/core.py
prarabdha/chats/disk.py
prarabdha/chats/segment_cache.py
prarabdha/cli/__init__.py
prarabdha/cli/cli.py
prarabdha/core/__init__.py
prarabdha/core/compression.py
prarabdha/core/encryption.py
prarabdha/core/export_manager.py
prarabdha/core/hash.py
prarabdha/core/kv_store.py
prarabdha/core/metadata_store.py
prarabdha/core/plugin_manager.py
prarabdha/core/redis_store.py
prarabdha/core/serializer.py
prarabdha/core/vector_index.py
prarabdha/rag/__init__.py
prarabdha/rag/chunk_index.py
prarabdha/tests/__init__.py
prarabdha/tests/test_kv_backends.py
prarabdha/tests/test_segment_cache.py
prarabdha/tests/test_vector_index.py
prarabdha/video/__init__.py
prarabdha/video/video_cache.py
prarabdha_cache-0.1.1.dist-info/licenses/LICENSE
prarabdha_cache-0.1.1.dist-info/METADATA
prarabdha_cache-0.1.1.dist-info/WHEEL
prarabdha_cache-0.1.1.dist-info/entry_points.txt
prarabdha_cache-0.1.1.dist-info/top_level.txt
prarabdha_cache-0.1.1.dist-info/RECORD
