Metadata-Version: 2.4
Name: prarabdha-cache
Version: 0.1.1
Summary: Modular AI Cache System for chats, audio, and video data ingestion
Author-email: Prarabdha Soni <prarabdha.soni@gmail.com>
License: MIT
Keywords: cache,ai,vector,rag,audio,video
Requires-Python: >=3.8
License-File: LICENSE
Requires-Dist: redis>=4.0
Requires-Dist: faiss-cpu
Requires-Dist: fastapi
Requires-Dist: uvicorn
Requires-Dist: numpy
Requires-Dist: aiohttp
Requires-Dist: pydantic
Requires-Dist: typer[all]
Requires-Dist: cryptography
Requires-Dist: pandas
Requires-Dist: pyarrow
Requires-Dist: psutil
Dynamic: license-file
